modal_or_local-0.1.1.dist-info/METADATA
modal_or_local-0.1.1.dist-info/WHEEL
modal_or_local-0.1.1.dist-info/licenses/LICENSE
modal_or_local/__init__.py
modal_or_local/logging_config.py
modal_or_local/logs/app.log
modal_or_local/modal_image_prep.py
modal_or_local/modal_or_local.py
modal_or_local/modal_or_local_copy.py
modal_or_local/modal_or_local_dir.py
modal_or_local-0.1.1.dist-info/RECORD
