Metadata-Version: 2.1
Name: modal_or_local
Version: 0.1.1
Summary: Utilities for working with files and directories in modal volumes or the local filesystem
Keywords: modal
Author-Email: Paul Wessling <paul@nowfree.org>
License: MIT
Project-URL: Repository, https://github.com/eyecantell/modal_or_local
Project-URL: Issues, https://github.com/eyecantell/modal_or_local/issues
Requires-Python: >=3.10
Requires-Dist: modal>=0.63.81
Requires-Dist: pytest>=6.0; extra == "dev"
Requires-Dist: GitPython; extra == "dev"
Provides-Extra: dev
